setup.py
src/leip/__init__.py
src/leip/cli.py
src/leip.egg-info/PKG-INFO
src/leip.egg-info/SOURCES.txt
src/leip.egg-info/dependency_links.txt
src/leip.egg-info/entry_points.txt
src/leip.egg-info/pbr.json
src/leip.egg-info/top_level.txt
test/test_1.py
test/test_2.py
test/test_3.py